topoloss/__init__.py
topoloss/core.py
topoloss/cortical_sheet/__init__.py
topoloss/cortical_sheet/common.py
topoloss/cortical_sheet/input.py
topoloss/cortical_sheet/output.py
topoloss/losses/__init__.py
topoloss/losses/laplacian_pyramid.py
topoloss/utils/__init__.py
topoloss/utils/getting_modules.py
topoloss-0.0.2.dist-info/METADATA
topoloss-0.0.2.dist-info/WHEEL
topoloss-0.0.2.dist-info/top_level.txt
topoloss-0.0.2.dist-info/RECORD
