Metadata-Version: 2.1
Name: topoloss
Version: 0.0.2
Summary: topoloss
Home-page: https://github.com/toponets/topoloss
Author: Mayukh Deb, Mainak Deb, N. Apurva Ratan Murty
Author-email: mayukhmainak2000@gmail.com, mayukh@gatech.edu
Classifier: Programming Language :: Python :: 3
Classifier: Operating System :: OS Independent
Requires-Dist: einops
Requires-Dist: torchtyping
